isiflask_core/Environment.py
isiflask_core/__init__.py
isiflask_core/app/Controllers/BaseController.py
isiflask_core/app/Data/BaseModel.py
isiflask_core/app/Data/Enum/http_status_code.py
isiflask_core/app/Data/Enum/request_parts.py
isiflask_core/app/Data/Interfaces/PaginationResult.py
isiflask_core/app/Data/Interfaces/ResourceReference.py
isiflask_core/app/Exceptions/APIException.py
isiflask_core/app/Services/BaseService.py
isiflask_core/app/Validators/RequestValidator.py
isiflask_core/config/database.py
isiflask_core/database/DBConnection.py
isiflask_core/utils/http_utils.py
isiflask_core-0.1.1.dist-info/METADATA
isiflask_core-0.1.1.dist-info/WHEEL
isiflask_core-0.1.1.dist-info/RECORD
