Metadata-Version: 2.1
Name: isiflask-core
Version: 0.1.1
Summary: 
Author: David De Los Santos Cuy Sánchez
Author-email: david.cuy.sanchez@gmail.com
Requires-Python: >=3.9,<4.0
Classifier: Programming Language :: Python :: 3
Classifier: Programming Language :: Python :: 3.9
Classifier: Programming Language :: Python :: 3.10
Classifier: Programming Language :: Python :: 3.11
Classifier: Programming Language :: Python :: 3.12
Requires-Dist: Flask (>=2.1.2,<3.0.0)
Requires-Dist: Flask-Cors (>=3.0.10,<4.0.0)
Requires-Dist: Flask-Migrate (>=3.1.0,<4.0.0)
Requires-Dist: Flask-SQLAlchemy (>=2.5.1,<3.0.0)
Requires-Dist: SQLAlchemy (>=1.4.36,<2.0.0)
Requires-Dist: alembic (>=1.7.7,<2.0.0)
Requires-Dist: python-dotenv (>=0.20.0,<0.21.0)
